anaconda_assistant_mcp/__init__.py
anaconda_assistant_mcp/_version.py
anaconda_assistant_mcp/plugin.py
anaconda_assistant_mcp/server.py
anaconda_assistant_mcp/tools_core/create_environment.py
anaconda_assistant_mcp/tools_core/environment_details.py
anaconda_assistant_mcp/tools_core/list_environment.py
anaconda_assistant_mcp/tools_core/remove_environment.py
anaconda_assistant_mcp/tools_core/shared.py
anaconda_assistant_mcp/tools_core/update_environment.py
anaconda_assistant_mcp-0.3.0.dist-info/METADATA
anaconda_assistant_mcp-0.3.0.dist-info/WHEEL
anaconda_assistant_mcp-0.3.0.dist-info/entry_points.txt
anaconda_assistant_mcp-0.3.0.dist-info/licenses/LICENSE
anaconda_assistant_mcp-0.3.0.dist-info/RECORD
