Metadata-Version: 2.4
Name: anaconda-assistant-mcp
Version: 0.3.0
Summary: The Anaconda Assistant MCP plugin
License: BSD-3-Clause
License-File: LICENSE
Requires-Python: >=3.10
Requires-Dist: fastmcp==2.8.1
Provides-Extra: dev
Requires-Dist: mypy; extra == 'dev'
Requires-Dist: pytest; extra == 'dev'
Requires-Dist: pytest-cov; extra == 'dev'
Requires-Dist: pytest-mock; extra == 'dev'
Requires-Dist: tox; extra == 'dev'
Provides-Extra: publish
Requires-Dist: build; extra == 'publish'
Requires-Dist: twine; extra == 'publish'
Requires-Dist: wheel; extra == 'publish'
